Sellix/Blacklists.py
Sellix/Categories.py
Sellix/Coupons.py
Sellix/Feedback.py
Sellix/Orders.py
Sellix/Payments.py
Sellix/Products.py
Sellix/Queries.py
Sellix/__init__.py
Sellix-1.0.1.dist-info/LICENSE
Sellix-1.0.1.dist-info/METADATA
Sellix-1.0.1.dist-info/WHEEL
Sellix-1.0.1.dist-info/top_level.txt
Sellix-1.0.1.dist-info/RECORD
