Metadata-Version: 2.1
Name: Sellix
Version: 1.0.1
Summary: Python Sellix Wrapper
Home-page: https://github.com/xFueY/Sellix/
Author: xFueY
Author-email: xFueY@protonmail.com
License: MIT
Keywords: Sellix
Platform: UNKNOWN
Classifier: Development Status :: 5 - Production/Stable
Classifier: Intended Audience :: Developers
Classifier: License :: OSI Approved :: MIT License
Classifier: Natural Language :: English
Classifier: Programming Language :: Python :: 3.8
Requires-Dist: requests
